unreal_script_editor/__init__.py
unreal_script_editor/config.txt
unreal_script_editor/main.py
unreal_script_editor/outputTextWidget.py
unreal_script_editor/startup.py
unreal_script_editor/codeEditor/.gitignore
unreal_script_editor/codeEditor/README.md
unreal_script_editor/codeEditor/__init__.py
unreal_script_editor/codeEditor/codeEditor.py
unreal_script_editor/codeEditor/main.py
unreal_script_editor/codeEditor/highlighter/__init__.py
unreal_script_editor/codeEditor/highlighter/jsonHighlight.py
unreal_script_editor/codeEditor/highlighter/pyHighlight.py
unreal_script_editor/icons/clearAll.png
unreal_script_editor/icons/clearHistory.png
unreal_script_editor/icons/clearInput.png
unreal_script_editor/icons/execute.png
unreal_script_editor/icons/executeAll.png
unreal_script_editor/ui/__init__.py
unreal_script_editor/ui/output_text_widget.py
unreal_script_editor/ui/output_text_widget.ui
unreal_script_editor/ui/script_editor.py
unreal_script_editor/ui/script_editor.ui
unreal_script_editor-0.0.3.dist-info/LICENSE
unreal_script_editor-0.0.3.dist-info/METADATA
unreal_script_editor-0.0.3.dist-info/WHEEL
unreal_script_editor-0.0.3.dist-info/top_level.txt
unreal_script_editor-0.0.3.dist-info/RECORD
