Metadata-Version: 2.1
Name: unreal-script-editor
Version: 0.0.3
Summary: A Qt Python script editor, styled in Unreal stylesheet
Author: Lei Xingyu, Hannes Delbeke
License: MIT License
Project-URL: Homepage, https://github.com/leixingyu/unrealScriptEditor
Project-URL: Source, https://github.com/leixingyu/unrealScriptEditor
Keywords: unreal,scripter
Classifier: Programming Language :: Python :: 3.7
Requires-Python: >=3.4
License-File: LICENSE
Requires-Dist: unreal-stylesheet
Requires-Dist: PySide6
Requires-Dist: importlib-metadata ; python_version < "3.7"
